collective.fhirpath-0.8.0-py3.7-nspkg.pth
collective/fhirpath/__init__.py
collective/fhirpath/adapters.py
collective/fhirpath/adapters.zcml
collective/fhirpath/configure.zcml
collective/fhirpath/dialect.py
collective/fhirpath/engine.py
collective/fhirpath/i18n.py
collective/fhirpath/interfaces.py
collective/fhirpath/patch.py
collective/fhirpath/profiles.zcml
collective/fhirpath/setuphandlers.py
collective/fhirpath/testing.py
collective/fhirpath/upgrades.py
collective/fhirpath/upgrades.zcml
collective/fhirpath/utils.py
collective/fhirpath/zcatalog.py
collective/fhirpath/EsIndexes/EsFhirFieldIndex.py
collective/fhirpath/EsIndexes/__init__.py
collective/fhirpath/PluginIndexes/FHIRIndex.py
collective/fhirpath/PluginIndexes/__init__.py
collective/fhirpath/PluginIndexes/index.gif
collective/fhirpath/PluginIndexes/dtml/addFhirFieldIndexForm.dtml
collective/fhirpath/PluginIndexes/dtml/manageFhirFieldIndex.dtml
collective/fhirpath/browser/__init__.py
collective/fhirpath/browser/configure.zcml
collective/fhirpath/browser/overrides/.gitkeep
collective/fhirpath/browser/static/.gitkeep
collective/fhirpath/browser/static/ES_MAPPINGS/R4/Account.mapping.json
collective/fhirpath/browser/static/ES_MAPPINGS/R4/ActivityDefinition.mapping.json
collective/fhirpath/browser/static/ES_MAPPINGS/R4/AdverseEvent.mapping.json
collective/fhirpath/browser/static/ES_MAPPINGS/R4/AllergyIntolerance.mapping.json
collective/fhirpath/browser/static/ES_MAPPINGS/R4/Appointment.mapping.json
collective/fhirpath/browser/static/ES_MAPPINGS/R4/AppointmentResponse.mapping.json
collective/fhirpath/browser/static/ES_MAPPINGS/R4/AuditEvent.mapping.json
collective/fhirpath/browser/static/ES_MAPPINGS/R4/Basic.mapping.json
collective/fhirpath/browser/static/ES_MAPPINGS/R4/BiologicallyDerivedProduct.mapping.json
collective/fhirpath/browser/static/ES_MAPPINGS/R4/BodyStructure.mapping.json
collective/fhirpath/browser/static/ES_MAPPINGS/R4/CapabilityStatement.mapping.json
collective.fhirpath-0.8.0.dist-info/LICENSE.GPL
collective.fhirpath-0.8.0.dist-info/LICENSE.rst
collective.fhirpath-0.8.0.dist-info/METADATA
collective.fhirpath-0.8.0.dist-info/WHEEL
collective.fhirpath-0.8.0.dist-info/entry_points.txt
collective.fhirpath-0.8.0.dist-info/namespace_packages.txt
collective.fhirpath-0.8.0.dist-info/top_level.txt
collective.fhirpath-0.8.0.dist-info/RECORD
