Metadata-Version: 2.1
Name: collective.fhirpath
Version: 0.8.0
Summary: Plone powered provider for fhirpath
Home-page: https://github.com/nazrulworld/collective.fhirpath
Author: Md Nazrul Islam
Author-email: email2nazru@gmail.com
License: GPL version 2
Project-URL: PyPI, https://pypi.python.org/pypi/collective.fhirpath
Project-URL: Source, https://github.com/nazrulworld/collective.fhirpath
Project-URL: Tracker, https://github.com/nazrulworld/collective.fhirpath/issues
Project-URL: Documentation, https://collective-fhirpath.readthedocs.io/en/latest/
Keywords: Python Plone FHIR Healthcare HL7
Platform: UNKNOWN
Classifier: Environment :: Web Environment
Classifier: Development Status :: 4 - Beta
Classifier: Framework :: Plone
Classifier: Framework :: Plone :: Addon
Classifier: Framework :: Plone :: 5.2
Classifier: Framework :: Plone :: 5.3
Classifier: Programming Language :: Python
Classifier: Programming Language :: Python :: 3.6
Classifier: Programming Language :: Python :: 3.7
Classifier: Programming Language :: Python :: 3.8
Classifier: Programming Language :: Python :: 3.9
Classifier: Operating System :: OS Independent
Classifier: License :: OSI Approved :: GNU General Public License v2 (GPLv2)
Requires-Python: >=3.6
Requires-Dist: setuptools
Requires-Dist: z3c.jbot
Requires-Dist: plone.restapi
Requires-Dist: plone.app.dexterity
Requires-Dist: collective.elasticsearch (<4.0.0,>=3.0.5)
Requires-Dist: plone.app.fhirfield (<5.0.0,>=4.2.0)
Requires-Dist: fhirpath (>=0.10.5)
Requires-Dist: fhir.resources[orjson] (>=6.1.0)
Provides-Extra: docs
Requires-Dist: sphinx ; extra == 'docs'
Requires-Dist: sphinx-rtd-theme ; extra == 'docs'
Requires-Dist: sphinxcontrib-httpdomain ; extra == 'docs'
Requires-Dist: sphinxcontrib-httpexample ; extra == 'docs'
Provides-Extra: test
Requires-Dist: plone.app.testing ; extra == 'test'
Requires-Dist: plone.app.contenttypes ; extra == 'test'
Requires-Dist: plone.app.robotframework[debug] ; extra == 'test'
Requires-Dist: collective.MockMailHost ; extra == 'test'
Requires-Dist: sphinx ; extra == 'test'
Requires-Dist: sphinx-rtd-theme ; extra == 'test'
Requires-Dist: sphinxcontrib-httpdomain ; extra == 'test'
Requires-Dist: sphinxcontrib-httpexample ; extra == 'test'
